{"status": "OK", "usage": "By accessing AlchemyAPI or using information generated by AlchemyAPI, you are agreeing to be bound by the AlchemyAPI Terms of Use: http://www.alchemyapi.com/company/terms.html", "url": "", "language": "english", "entities": [{"relevance": "0.943138", "count": "29", "type": "Person", "text": "Bran"}, {"relevance": "0.462951", "count": "12", "type": "Person", "text": "crow"}, {"relevance": "0.188856", "count": "2", "type": "Person", "text": "Maester Luwin"}, {"relevance": "0.171278", "count": "2", "type": "Person", "text": "Robb"}, {"relevance": "0.14785", "count": "1", "type": "Person", "text": "Winterfell"}, {"relevance": "0.142172", "count": "1", "type": "Company", "text": "Trident"}, {"relevance": "0.141166", "count": "2", "type": "City", "text": "Winterfell"}, {"relevance": "0.140154", "count": "1", "type": "Person", "text": "Ser Rodrik"}, {"relevance": "0.1366", "count": "1", "type": "GeographicFeature", "disambiguated": {"yago": "http://yago-knowledge.org/resource/Lake_Turkana", "name": "Lake Turkana", "freebase": "http://rdf.freebase.com/ns/m.02hnps", "subType": ["Location", "BodyOfWater", "Lake"], "dbpedia": "http://dbpedia.org/resource/Lake_Turkana", "geo": "3.05 36.016666666666666"}, "text": "Jade Sea"}, {"relevance": "0.135069", "count": "1", "type": "Person", "text": "Hodor"}, {"relevance": "0.134792", "count": "1", "type": "Person", "text": "Sansa"}, {"relevance": "0.134133", "count": "1", "type": "Organization", "text": "eagles"}, {"relevance": "0.133082", "count": "1", "type": "GeographicFeature", "text": "green Dothraki sea"}, {"relevance": "0.132641", "count": "1", "type": "Person", "text": "Jon"}, {"relevance": "0.128588", "count": "1", "type": "City", "text": "Mikken"}, {"relevance": "0.1269", "count": "1", "type": "Person", "text": "Arya"}, {"relevance": "0.123308", "count": "1", "type": "City", "text": "Vaes Dothrak"}, {"relevance": "0.120386", "count": "1", "type": "City", "text": "Asshai"}]}