{"status": "OK", "usage": "By accessing AlchemyAPI or using information generated by AlchemyAPI, you are agreeing to be bound by the AlchemyAPI Terms of Use: http://www.alchemyapi.com/company/terms.html", "url": "", "language": "english", "entities": [{"relevance": "0.870794", "count": "38", "type": "Person", "text": "Lord Petyr"}, {"relevance": "0.689037", "count": "41", "type": "Person", "text": "Alayne"}, {"relevance": "0.579916", "count": "27", "type": "Person", "text": "Lord Robert"}, {"relevance": "0.511141", "count": "12", "type": "Person", "text": "Lord Nestor Royce"}, {"relevance": "0.450612", "count": "16", "type": "Person", "text": "Ser Lyn Corbray"}, {"relevance": "0.425439", "count": "9", "type": "Person", "text": "Lord Littlefinger"}, {"relevance": "0.380727", "count": "7", "type": "Movie", "text": "The Lord Protector"}, {"relevance": "0.35137", "count": "12", "type": "Person", "text": "Benedar Belmore"}, {"relevance": "0.341197", "count": "5", "type": "City", "text": "Alayne"}, {"relevance": "0.336766", "count": "5", "type": "Person", "text": "Lord Nestor"}, {"relevance": "0.335508", "count": "10", "type": "Person", "text": "Ser Lyn"}, {"relevance": "0.321056", "count": "12", "type": "Person", "text": "Lady Lysa"}, {"relevance": "0.313358", "count": "5", "type": "Person", "text": "Petyr Baelish"}, {"relevance": "0.311701", "count": "10", "type": "City", "text": "Eyrie"}, {"relevance": "0.308222", "count": "13", "type": "Person", "text": "Anya Waynwood"}, {"relevance": "0.307298", "count": "13", "type": "Person", "text": "Gilwood Hunter"}, {"relevance": "0.306778", "count": "6", "type": "Organization", "text": "Lords Declarant"}, {"relevance": "0.278381", "count": "6", "type": "Person", "text": "Lord Lyonel Corbray"}, {"relevance": "0.270617", "count": "3", "type": "Person", "text": "Lord Protector"}, {"relevance": "0.25994", "count": "9", "type": "Person", "text": "Horton Redfort"}, {"relevance": "0.259354", "count": "6", "type": "Person", "text": "Symond Templeton"}, {"relevance": "0.250784", "count": "6", "type": "Person", "text": "Lord Yohn"}, {"relevance": "0.244718", "count": "2", "type": "Person", "text": "Alayne Stone"}, {"relevance": "0.240707", "count": "9", "type": "City", "text": "Runestone"}, {"relevance": "0.233893", "count": "1", "type": "GeographicFeature", "text": "Lord Petyr"}, {"relevance": "0.221586", "count": "6", "type": "GeographicFeature", "text": "Bronze Yohn"}, {"relevance": "0.214555", "count": "5", "type": "Person", "text": "Maester Colemon"}, {"relevance": "0.209199", "count": "1", "type": "GeographicFeature", "text": "Lord Yohn"}, {"relevance": "0.203627", "count": "1", "type": "GeographicFeature", "text": "Lord Frey"}, {"relevance": "0.195886", "count": "3", "type": "Facility", "text": "Longbow Hall"}, {"relevance": "0.19269", "count": "1", "type": "Facility", "text": "Lord Belmore blustered"}, {"relevance": "0.192571", "count": "5", "type": "Person", "text": "Gretchel"}, {"relevance": "0.191419", "count": "3", "type": "Company", "text": "Sky"}, {"relevance": "0.190454", "count": "1", "type": "GeographicFeature", "text": "Petyr Baelish"}, {"relevance": "0.190369", "count": "1", "type": "GeographicFeature", "text": "Lord Tywin"}, {"relevance": "0.190188", "count": "3", "type": "City", "text": "Riverrun"}, {"relevance": "0.184549", "count": "3", "type": "Company", "text": "Sansa"}, {"relevance": "0.182822", "count": "4", "type": "Person", "text": "Jon Arryn"}, {"relevance": "0.180439", "count": "5", "type": "Degree", "text": "Corbray"}, {"relevance": "0.178585", "count": "2", "type": "Person", "text": "Mya"}, {"relevance": "0.176639", "count": "3", "type": "Person", "text": "Gates"}, {"relevance": "0.17502", "count": "1", "type": "Person", "text": "Lord Grafton"}, {"relevance": "0.175001", "count": "1", "type": "Person", "text": "Lord Waxley"}, {"relevance": "0.173243", "count": "2", "type": "OperatingSystem", "text": "windows"}, {"relevance": "0.172148", "count": "2", "type": "City", "text": "Gretchel"}, {"relevance": "0.170022", "count": "2", "type": "GeographicFeature", "text": "Maester Colemon"}, {"relevance": "0.169905", "count": "2", "type": "City", "text": "Ninestars"}, {"relevance": "0.16957", "count": "1", "type": "Person", "text": "Lord Eon"}, {"relevance": "0.169489", "count": "1", "type": "Person", "text": "Lysa Arryn"}, {"relevance": "0.168953", "count": "2", "type": "Person", "text": "Lady Anya"}]}